pypipegraph2-3.4.2.dist-info/METADATA
pypipegraph2-3.4.2.dist-info/WHEEL
pypipegraph2-3.4.2.dist-info/entry_points.txt
pypipegraph2-3.4.2.dist-info/licenses/AUTHORS.rst
pypipegraph2/ppg_traceback.py
pypipegraph2/testing/__init__.py
pypipegraph2/testing/fixtures.py
pypipegraph2/entry_points.py
pypipegraph2/exceptions.py
pypipegraph2/util.py
pypipegraph2/__init__.py
pypipegraph2/interactive.py
pypipegraph2/enums.py
pypipegraph2/graph.py
pypipegraph2/ppg1_compatibility.py
pypipegraph2/runner.py
pypipegraph2/cli.py
pypipegraph2/history_comparisons.py
pypipegraph2/parallel.py
pypipegraph2/jobs.py
pypipegraph2/hashers.py
pypipegraph2/job_status.py
pypipegraph2/pypipegraph2.abi3.so
pypipegraph2-3.4.2.dist-info/RECORD
