Metadata-Version: 2.3
Name: pypipegraph2
Version: 3.4.2
Classifier: Development Status :: 4 - Beta
Classifier: Programming Language :: Python
Classifier: Programming Language :: Rust
Requires-Dist: loguru
Requires-Dist: rich
Requires-Dist: xxhash
Requires-Dist: wrapt
Requires-Dist: deepdiff
Requires-Dist: psutil
Requires-Dist: networkx
Requires-Dist: filelock
Requires-Dist: pyzstd
Requires-Dist: lib-programname
Requires-Dist: textual
Requires-Dist: flake8 ; extra == 'dev'
Requires-Dist: pytest ; extra == 'dev'
Requires-Dist: pytest-cov ; extra == 'dev'
Requires-Dist: pre-commit ; extra == 'dev'
Requires-Dist: black ; extra == 'dev'
Requires-Dist: flake8 ; extra == 'test'
Requires-Dist: pytest ; extra == 'test'
Requires-Dist: pytest-cov ; extra == 'test'
Provides-Extra: dev
Provides-Extra: test
License-File: AUTHORS.rst
Summary: Advanced python 'what changed and what do we need to do' tracking
Author-email: Florian Finkernagel <finkernagel@imt.uni-marburg.de>
License: MIT License
Requires-Python: >=3.8
Project-URL: homepage, https://github.com/TyberiusPrime/pypipegraph2
